MANIFEST.in
changelog.rst
readme.rst
setup.py
TemplatingBWC.egg-info/PKG-INFO
TemplatingBWC.egg-info/SOURCES.txt
TemplatingBWC.egg-info/dependency_links.txt
TemplatingBWC.egg-info/not-zip-safe
TemplatingBWC.egg-info/requires.txt
TemplatingBWC.egg-info/top_level.txt
templatingbwc/__init__.py
templatingbwc/version.txt
templatingbwc/static/blueprint-css/ie.css
templatingbwc/static/blueprint-css/print.css
templatingbwc/static/blueprint-css/screen.css
templatingbwc/static/blueprint-css/src/grid.png
templatingbwc/static/css/select2-spinner.gif
templatingbwc/static/css/select2.css
templatingbwc/static/css/select2.png
templatingbwc/static/css/select2x2.png
templatingbwc/static/js/jquery-ui.complete.min.js
templatingbwc/static/js/jquery.hoverIntent.min.js
templatingbwc/static/js/jquery.min.js
templatingbwc/static/js/jquery.superfish.min.js
templatingbwc/static/js/select2.min.js
templatingbwc/static/templates-admin/css/jquery-ui.min.css
templatingbwc/static/templates-admin/css/superfish.css
templatingbwc/static/templates-admin/css/theme.css
templatingbwc/static/templates-admin/icons/accept.png
templatingbwc/static/templates-admin/icons/application_form_edit.png
templatingbwc/static/templates-admin/icons/arrow_down.png
templatingbwc/static/templates-admin/icons/arrow_up.png
templatingbwc/static/templates-admin/icons/black-x-12.png
templatingbwc/static/templates-admin/icons/cancel.png
templatingbwc/static/templates-admin/icons/delete.png
templatingbwc/static/templates-admin/icons/error.png
templatingbwc/static/templates-admin/icons/information.png
templatingbwc/static/templates-admin/icons/th_arrow_down.png
templatingbwc/static/templates-admin/icons/th_arrow_up.png
templatingbwc/static/templates-admin/images/blue_inset_background.png
templatingbwc/static/templates-admin/images/charcoal_inset_background.png
templatingbwc/static/templates-admin/images/dark_fine_grain_background.png
templatingbwc/static/templates-admin/images/gray_maze_background.png
templatingbwc/static/templates-admin/images/superfish_arrows.png
templatingbwc/static/templates-admin/images/white_down_arrow.gif
templatingbwc/static/templates-admin/images/white_up_arrow.gif
